{
  "Visibility": "VISIBLE",
  "Title": "Қыстық жаңарту🎄",
  "Description": "— Дорама және аниме каталогы жойылды (Сервердегі жаңартуларға байланысты)\n— Өзгертулер тізімі бөлімінің дизайны күшейтілді\n— Іздеу жүйесіне кірген кезде қосымшадан шығып кететін қателік жойылды\n— ToolBar жаңа дизайн\n— Релиз бөлімінде аздап дизайнды өзгерттік\n— Жаңа фрагменттер қосылды\n— Drawer алынып тасталынып замануи мәзір жасалынды\n— 4 жаңа уақытша сервер қосылды, толық ақпаратты баптаулардан көре аласыздар\n— Жобаны қолдау разделінің дизайны аздап өзгертілді\n— Аниме Цитаты разделінде енді аниме атын және кейіпкер есімін буферге көшіріп алу мүмкіндігі қосылды\nЖаңа раздел «Кесте» қосылды\n— Басты беттің дизайны аздап өзгертілді\n—Дыбыстама студиясын таңдау мүмкіндігі қосылды",
  "MainTextButton": "Жаңарту",
  "Cancelable": "true",
  "CancelButtonText": "Кейінірек жаңарту",
  "DownloadLink": "https://t.me/seele_off",
  "Version": "1.7"
}
